auxil/__init__.py
auxil/basicf.pyd
auxil/basicsecurityalgorithm.pyd
auxil/objdef.pyd
auxil-7.1.0.dist-info/LICENSE.txt
auxil-7.1.0.dist-info/METADATA
auxil-7.1.0.dist-info/WHEEL
auxil-7.1.0.dist-info/top_level.txt
auxil-7.1.0.dist-info/RECORD
